data_source_faker/__init__.py
data_source_faker/logging/__init__.py
data_source_faker/logging/logger_config.py
data_source_faker/logging/logging_mixin.py
data_source_faker/main.py
data_source_faker/models.py
data_source_faker/providers/__init__.py
data_source_faker/providers/database_column.py
data_source_faker/yaml/__init__.py
data_source_faker/yaml/dumper.py
data_source_faker-0.1.0.dist-info/METADATA
data_source_faker-0.1.0.dist-info/WHEEL
data_source_faker-0.1.0.dist-info/RECORD
